sunglass/__init__.py
sunglass/__main__.py
sunglass/log.py
sunglass/materials.py
sunglass/plot.py
sunglass/properties_and_settings.py
sunglass/run_calculation.py
sunglass/save_data.py
sunglass/solar_cells.py
sunglass/spectrum.py
sunglass/sunglass.py
sunglass-0.1.1.dist-info/LICENSE
sunglass-0.1.1.dist-info/WHEEL
sunglass-0.1.1.dist-info/METADATA
sunglass-0.1.1.dist-info/RECORD
